nso_live_status/__init__.py
nso_live_status/nso_live_status.py
nso_live_status-1.0.6.dist-info/LICENSE
nso_live_status-1.0.6.dist-info/METADATA
nso_live_status-1.0.6.dist-info/WHEEL
nso_live_status-1.0.6.dist-info/top_level.txt
nso_live_status-1.0.6.dist-info/RECORD
