Metadata-Version: 2.1
Name: nso-live-status
Version: 1.0.6
Summary: Retrieve cli result and parse it using NSO live status and PyATS parsers
Home-page: https://github.com/rtrjl/nso_live_status
Author: Rodolphe Trujillo
Author-email: rodtruji@cisco.com
License: Cisco Sample Code License, Version 1.1
Classifier: Topic :: System :: Networking
License-File: LICENSE
Requires-Dist: pyats-parser (>=1.0.7)
